MANIFEST.in
README.md
requirements.txt
setup.py
p2p_python/__init__.py
p2p_python/config.py
p2p_python/core.py
p2p_python/serializer.py
p2p_python/server.py
p2p_python/user.py
p2p_python/utils.py
p2p_python.egg-info/PKG-INFO
p2p_python.egg-info/SOURCES.txt
p2p_python.egg-info/dependency_links.txt
p2p_python.egg-info/requires.txt
p2p_python.egg-info/top_level.txt
p2p_python/tool/__init__.py
p2p_python/tool/traffic.py
p2p_python/tool/upnpc.py
p2p_python/tool/utils.py