Metadata-Version: 2.1
Name: p2p-python
Version: 2.1.0
Summary: Simple peer2peer library.
Home-page: https://github.com/namuyan/p2p-python
Author: namuyan
License: MIT Licence
Platform: UNKNOWN
Classifier: Programming Language :: Python :: 3
Classifier: Programming Language :: Python :: 3.6
Classifier: License :: OSI Approved :: MIT License
Requires-Python: >=3.6
